pyworkon/__init__.py
pyworkon/__main__.py
pyworkon/config.py
pyworkon/db.py
pyworkon/exceptions.py
pyworkon/interfaces/__init__.py
pyworkon/interfaces/shell/__init__.py
pyworkon/interfaces/shell/command.py
pyworkon/interfaces/shell/commands/__init__.py
pyworkon/interfaces/shell/commands/clone.py
pyworkon/interfaces/shell/commands/help.py
pyworkon/interfaces/shell/commands/provider.py
pyworkon/interfaces/shell/commands/workon.py
pyworkon/interfaces/shell/plugin.py
pyworkon/interfaces/tui/__init__.py
pyworkon/interfaces/tui/tui.py
pyworkon/interfaces/tui/widgets/__init__.py
pyworkon/interfaces/tui/widgets/project_tree.py
pyworkon/project.py
pyworkon/providers/__init__.py
pyworkon/providers/bitbucket/__init__.py
pyworkon/providers/bitbucket/bitbucket.py
pyworkon/providers/bitbucket/consumer.py
pyworkon/providers/bitbucket/models.py
pyworkon/providers/github/__init__.py
pyworkon/providers/github/consumer.py
pyworkon/providers/github/github.py
pyworkon/providers/github/models.py
pyworkon/providers/gitlab/__init__.py
pyworkon/providers/gitlab/consumer.py
pyworkon/providers/gitlab/gitlab.py
pyworkon/providers/gitlab/models.py
pyworkon/providers/models.py
pyworkon-0.1.3.dist-info/WHEEL
pyworkon-0.1.3.dist-info/LICENSE
pyworkon-0.1.3.dist-info/METADATA
pyworkon-0.1.3.dist-info/entry_points.txt
pyworkon-0.1.3.dist-info/RECORD
