Metadata-Version: 2.1
Name: pyworkon
Version: 0.1.3
Summary: Software Development Project Management Tool
Home-page: https://github.com/chassing/pyworkon
License: MIT
Author: Christian Assing
Author-email: chris@ca-net.org
Requires-Python: >=3.10.0,<4.0.0
Classifier: License :: OSI Approved :: MIT License
Classifier: Programming Language :: Python :: 3
Classifier: Programming Language :: Python :: 3.10
Classifier: Programming Language :: Python :: 3.11
Classifier: Topic :: Software Development :: Build Tools
Classifier: Topic :: Software Development :: Libraries :: Python Modules
Requires-Dist: PyYAML (>=6.0,<7.0)
Requires-Dist: appdirs (>=1.4.4,<2.0.0)
Requires-Dist: asgiref (>=3.5.0,<4.0.0)
Requires-Dist: fuzzyfinder (>=2.1.0,<3.0.0)
Requires-Dist: httpx (>0.23.0)
Requires-Dist: orm[sqlite] (>=0.3.1,<0.4.0)
Requires-Dist: prompt-toolkit (>=3.0.28,<4.0.0)
Requires-Dist: pydantic (>=1.10.0,<2.0.0)
Requires-Dist: python-nubia (>=0.2b5,<0.3)
Requires-Dist: rich (>=13.1.0,<14.0.0)
Requires-Dist: rich-click (>=1.6.0,<2.0.0)
Requires-Dist: sqlalchemy (>=1.4.41,<2.0.0,!=1.4.42)
Requires-Dist: uplink-httpx (>=2.0,<3.0)
Project-URL: Bug Tracker, https://github.com/chassing/pyworkon/issues
Project-URL: Repository, https://github.com/chassing/pyworkon
